nichecompass/__init__.py
nichecompass/benchmarking/__init__.py
nichecompass/benchmarking/cas.py
nichecompass/benchmarking/clisis.py
nichecompass/benchmarking/gcs.py
nichecompass/benchmarking/metrics.py
nichecompass/benchmarking/mlami.py
nichecompass/benchmarking/nasw.py
nichecompass/benchmarking/utils.py
nichecompass/data/__init__.py
nichecompass/data/dataloaders.py
nichecompass/data/dataprocessors.py
nichecompass/data/datareaders.py
nichecompass/data/datasets.py
nichecompass/data/utils.py
nichecompass/models/__init__.py
nichecompass/models/basemodelmixin.py
nichecompass/models/nichecompass.py
nichecompass/models/utils.py
nichecompass/modules/__init__.py
nichecompass/modules/basemodulemixin.py
nichecompass/modules/losses.py
nichecompass/modules/vgaemodulemixin.py
nichecompass/modules/vgpgae.py
nichecompass/nn/__init__.py
nichecompass/nn/aggregators.py
nichecompass/nn/decoders.py
nichecompass/nn/encoders.py
nichecompass/nn/layercomponents.py
nichecompass/nn/layers.py
nichecompass/nn/utils.py
nichecompass/train/__init__.py
nichecompass/train/basetrainermixin.py
nichecompass/train/metrics.py
nichecompass/train/trainer.py
nichecompass/train/utils.py
nichecompass/utils/__init__.py
nichecompass/utils/analysis.py
nichecompass/utils/gene_programs.py
nichecompass/utils/multimodal_mapping.py
nichecompass/utils/utils.py
nichecompass-0.3.2.dist-info/METADATA
nichecompass-0.3.2.dist-info/WHEEL
nichecompass-0.3.2.dist-info/licenses/LICENSE
nichecompass-0.3.2.dist-info/RECORD
